localizedstringkit/__init__.py
localizedstringkit/command_line.py
localizedstringkit/detection.py
localizedstringkit/exceptions.py
localizedstringkit/files.py
localizedstringkit/logger.py
localizedstringkit-0.2.6.dist-info/METADATA
localizedstringkit-0.2.6.dist-info/WHEEL
localizedstringkit-0.2.6.dist-info/entry_points.txt
localizedstringkit-0.2.6.dist-info/RECORD
